pyperclip_plus/__init__.py
pyperclip_plus/clipboard_manager.py
pyperclip_plus-0.1.9.dist-info/METADATA
pyperclip_plus-0.1.9.dist-info/WHEEL
pyperclip_plus-0.1.9.dist-info/top_level.txt
pyperclip_plus-0.1.9.dist-info/RECORD
